{
	"info": {
		"_postman_id": "30606527-cc1a-4e8f-962d-c2346552e873",
		"name": "Api Doc",
		"schema": "https://schema.getpostman.com/json/collection/v2.1.0/collection.json"
	},
	"item": [
		{
			"name": "Clientes",
			"item": [
				{
					"name": "localhost:3000/clientes",
					"request": {
						"auth": {
							"type": "noauth"
						},
						"method": "POST",
						"header": [
							{
								"key": "Content-Type",
								"name": "Content-Type",
								"value": "application/json",
								"type": "text"
							},
							{
								"key": "",
								"value": "",
								"type": "text",
								"disabled": true
							},
							{
								"key": "",
								"value": "",
								"type": "text",
								"disabled": true
							}
						],
						"body": {
							"mode": "raw",
							"raw": "{\n\t\"nome\": \"Ana\",\n\t\"numeroCpfCnpj\": \"791.532.280-06\",\n\t\"email\": \"ana@email.com\",\n\t\"senha\": \"123456\"\n}",
							"options": {
								"raw": {
									"language": "json"
								}
							}
						},
						"url": {
							"raw": "localhost:3000/clientes",
							"host": [
								"localhost"
							],
							"port": "3000",
							"path": [
								"clientes"
							]
						}
					},
					"response": []
				},
				{
					"name": "localhost:3000/clientes/login",
					"request": {
						"auth": {
							"type": "noauth"
						},
						"method": "POST",
						"header": [
							{
								"key": "Content-Type",
								"name": "Content-Type",
								"value": "application/json",
								"type": "text"
							},
							{
								"key": "",
								"value": "",
								"type": "text",
								"disabled": true
							},
							{
								"key": "",
								"value": "",
								"type": "text",
								"disabled": true
							}
						],
						"body": {
							"mode": "raw",
							"raw": "{\n\t\"email\": \"ana@email.com\",\n\t\"senha\": \"123456\"\n}",
							"options": {
								"raw": {
									"language": "json"
								}
							}
						},
						"url": {
							"raw": "localhost:3000/clientes/login",
							"host": [
								"localhost"
							],
							"port": "3000",
							"path": [
								"clientes",
								"login"
							]
						}
					},
					"response": []
				},
				{
					"name": "localhost:3000/clientes",
					"request": {
						"auth": {
							"type": "bearer",
							"bearer": [
								{
									"key": "token",
									"value": "eyJhbGciOiJIUzI1NiIsInR5cCI6IkpXVCJ9.eyJpZCI6MSwiZW1haWwiOiJhbmFAZW1haWwuY29tIiwiaWF0IjoxNTc4MjQ2Mjk1LCJleHAiOjE1NzgzMzI2OTV9.wz2XXejN9c7SQNZtOke5537URts1-ShekfwO0_MwFCE",
									"type": "string"
								}
							]
						},
						"method": "GET",
						"header": [
							{
								"key": "Content-Type",
								"name": "Content-Type",
								"value": "application/json",
								"type": "text"
							},
							{
								"key": "",
								"value": "",
								"type": "text",
								"disabled": true
							},
							{
								"key": "",
								"value": "",
								"type": "text",
								"disabled": true
							}
						],
						"url": {
							"raw": "localhost:3000/clientes",
							"host": [
								"localhost"
							],
							"port": "3000",
							"path": [
								"clientes"
							]
						}
					},
					"response": []
				},
				{
					"name": "localhost:3000/clientes/1",
					"request": {
						"auth": {
							"type": "bearer",
							"bearer": [
								{
									"key": "token",
									"value": "eyJhbGciOiJIUzI1NiIsInR5cCI6IkpXVCJ9.eyJpZCI6MSwiZW1haWwiOiJhbmFAZW1haWwuY29tIiwiaWF0IjoxNTc4MjQ2Mjk1LCJleHAiOjE1NzgzMzI2OTV9.wz2XXejN9c7SQNZtOke5537URts1-ShekfwO0_MwFCE",
									"type": "string"
								}
							]
						},
						"method": "GET",
						"header": [],
						"url": {
							"raw": "localhost:3000/clientes/1",
							"host": [
								"localhost"
							],
							"port": "3000",
							"path": [
								"clientes",
								"1"
							]
						}
					},
					"response": []
				},
				{
					"name": "localhost:3000/clientes/1",
					"request": {
						"auth": {
							"type": "bearer",
							"bearer": [
								{
									"key": "token",
									"value": "eyJhbGciOiJIUzI1NiIsInR5cCI6IkpXVCJ9.eyJpZCI6MSwiZW1haWwiOiJhbmFAZW1haWwuY29tIiwiaWF0IjoxNTc4MjQ2Mjk1LCJleHAiOjE1NzgzMzI2OTV9.wz2XXejN9c7SQNZtOke5537URts1-ShekfwO0_MwFCE",
									"type": "string"
								}
							]
						},
						"method": "PUT",
						"header": [
							{
								"key": "Content-Type",
								"name": "Content-Type",
								"value": "application/json",
								"type": "text"
							}
						],
						"body": {
							"mode": "raw",
							"raw": "{\n\t\"nome\": \"Novo nome\",\n\t\"numeroCpfCnpj\": \"791.532.280-06\",\n\t\"email\": \"novo-email@email.com\",\n\t\"senha\": \"123456\"\n}",
							"options": {
								"raw": {
									"language": "json"
								}
							}
						},
						"url": {
							"raw": "localhost:3000/clientes/1",
							"host": [
								"localhost"
							],
							"port": "3000",
							"path": [
								"clientes",
								"1"
							]
						}
					},
					"response": []
				},
				{
					"name": "localhost:3000/clientes/1",
					"request": {
						"auth": {
							"type": "bearer",
							"bearer": [
								{
									"key": "token",
									"value": "eyJhbGciOiJIUzI1NiIsInR5cCI6IkpXVCJ9.eyJpZCI6MSwiZW1haWwiOiJhbmFAZW1haWwuY29tIiwiaWF0IjoxNTc4MjQ2Mjk1LCJleHAiOjE1NzgzMzI2OTV9.wz2XXejN9c7SQNZtOke5537URts1-ShekfwO0_MwFCE",
									"type": "string"
								}
							]
						},
						"method": "DELETE",
						"header": [],
						"url": {
							"raw": "localhost:3000/clientes/1",
							"host": [
								"localhost"
							],
							"port": "3000",
							"path": [
								"clientes",
								"1"
							]
						}
					},
					"response": []
				}
			],
			"protocolProfileBehavior": {}
		},
		{
			"name": "Categorias",
			"item": [
				{
					"name": "localhost:3000/categorias",
					"request": {
						"auth": {
							"type": "bearer",
							"bearer": [
								{
									"key": "token",
									"value": "eyJhbGciOiJIUzI1NiIsInR5cCI6IkpXVCJ9.eyJpZCI6MiwiZW1haWwiOiJhbmFAZW1haWwuY29tIiwiaWF0IjoxNTc4MjQ3MjY5LCJleHAiOjE1NzgzMzM2Njl9.WBb_IE6e6VRCTHtQslhqSO-6uCAk_IDibRzh1Q56VjY",
									"type": "string"
								}
							]
						},
						"method": "POST",
						"header": [
							{
								"key": "Content-Type",
								"name": "Content-Type",
								"value": "application/json",
								"type": "text"
							}
						],
						"body": {
							"mode": "raw",
							"raw": "{\n\t\"descricao\": \"Produtos de limpeza\"\n}",
							"options": {
								"raw": {
									"language": "json"
								}
							}
						},
						"url": {
							"raw": "localhost:3000/categorias",
							"host": [
								"localhost"
							],
							"port": "3000",
							"path": [
								"categorias"
							]
						}
					},
					"response": []
				},
				{
					"name": "localhost:3000/categorias",
					"request": {
						"auth": {
							"type": "bearer",
							"bearer": [
								{
									"key": "token",
									"value": "eyJhbGciOiJIUzI1NiIsInR5cCI6IkpXVCJ9.eyJpZCI6MiwiZW1haWwiOiJhbmFAZW1haWwuY29tIiwiaWF0IjoxNTc4MjQ3MjY5LCJleHAiOjE1NzgzMzM2Njl9.WBb_IE6e6VRCTHtQslhqSO-6uCAk_IDibRzh1Q56VjY",
									"type": "string"
								}
							]
						},
						"method": "GET",
						"header": [],
						"url": {
							"raw": "localhost:3000/categorias",
							"host": [
								"localhost"
							],
							"port": "3000",
							"path": [
								"categorias"
							]
						}
					},
					"response": []
				},
				{
					"name": "localhost:3000/categorias/1",
					"request": {
						"auth": {
							"type": "bearer",
							"bearer": [
								{
									"key": "token",
									"value": "eyJhbGciOiJIUzI1NiIsInR5cCI6IkpXVCJ9.eyJpZCI6MiwiZW1haWwiOiJhbmFAZW1haWwuY29tIiwiaWF0IjoxNTc4MjQ3MjY5LCJleHAiOjE1NzgzMzM2Njl9.WBb_IE6e6VRCTHtQslhqSO-6uCAk_IDibRzh1Q56VjY",
									"type": "string"
								}
							]
						},
						"method": "GET",
						"header": [],
						"url": {
							"raw": "localhost:3000/categorias/1",
							"host": [
								"localhost"
							],
							"port": "3000",
							"path": [
								"categorias",
								"1"
							]
						}
					},
					"response": []
				},
				{
					"name": "localhost:3000/categorias/1",
					"request": {
						"auth": {
							"type": "bearer",
							"bearer": [
								{
									"key": "token",
									"value": "eyJhbGciOiJIUzI1NiIsInR5cCI6IkpXVCJ9.eyJpZCI6MiwiZW1haWwiOiJhbmFAZW1haWwuY29tIiwiaWF0IjoxNTc4MjQ3MjY5LCJleHAiOjE1NzgzMzM2Njl9.WBb_IE6e6VRCTHtQslhqSO-6uCAk_IDibRzh1Q56VjY",
									"type": "string"
								}
							]
						},
						"method": "PUT",
						"header": [
							{
								"key": "Content-Type",
								"name": "Content-Type",
								"value": "application/json",
								"type": "text"
							}
						],
						"body": {
							"mode": "raw",
							"raw": "{\n\t\"descricao\": \"Categoria atualizada\"\n}",
							"options": {
								"raw": {
									"language": "json"
								}
							}
						},
						"url": {
							"raw": "localhost:3000/categorias/1",
							"host": [
								"localhost"
							],
							"port": "3000",
							"path": [
								"categorias",
								"1"
							]
						}
					},
					"response": []
				},
				{
					"name": "localhost:3000/categorias/1",
					"request": {
						"auth": {
							"type": "bearer",
							"bearer": [
								{
									"key": "token",
									"value": "eyJhbGciOiJIUzI1NiIsInR5cCI6IkpXVCJ9.eyJpZCI6MiwiZW1haWwiOiJhbmFAZW1haWwuY29tIiwiaWF0IjoxNTc4MjQ3MjY5LCJleHAiOjE1NzgzMzM2Njl9.WBb_IE6e6VRCTHtQslhqSO-6uCAk_IDibRzh1Q56VjY",
									"type": "string"
								}
							]
						},
						"method": "DELETE",
						"header": [
							{
								"key": "Content-Type",
								"name": "Content-Type",
								"value": "application/json",
								"type": "text"
							}
						],
						"url": {
							"raw": "localhost:3000/categorias/1",
							"host": [
								"localhost"
							],
							"port": "3000",
							"path": [
								"categorias",
								"1"
							]
						}
					},
					"response": []
				}
			],
			"protocolProfileBehavior": {}
		},
		{
			"name": "Produtos",
			"item": [
				{
					"name": "localhost:3000/produtos",
					"request": {
						"auth": {
							"type": "bearer",
							"bearer": [
								{
									"key": "token",
									"value": "eyJhbGciOiJIUzI1NiIsInR5cCI6IkpXVCJ9.eyJpZCI6MiwiZW1haWwiOiJhbmFAZW1haWwuY29tIiwiaWF0IjoxNTc4MjQ3MjY5LCJleHAiOjE1NzgzMzM2Njl9.WBb_IE6e6VRCTHtQslhqSO-6uCAk_IDibRzh1Q56VjY",
									"type": "string"
								}
							]
						},
						"method": "POST",
						"header": [
							{
								"key": "Content-Type",
								"name": "Content-Type",
								"value": "application/json",
								"type": "text"
							}
						],
						"body": {
							"mode": "raw",
							"raw": "{\n\t\"descricao\": \"Sabonete\",\n\t\"quantidade\": \"50\",\n\t\"valor\": 5.00,\n\t\"categoriaId\": 2\n}",
							"options": {
								"raw": {
									"language": "json"
								}
							}
						},
						"url": {
							"raw": "localhost:3000/produtos",
							"host": [
								"localhost"
							],
							"port": "3000",
							"path": [
								"produtos"
							]
						}
					},
					"response": []
				},
				{
					"name": "localhost:3000/produtos",
					"request": {
						"auth": {
							"type": "noauth"
						},
						"method": "GET",
						"header": [
							{
								"key": "Content-Type",
								"name": "Content-Type",
								"value": "application/json",
								"type": "text"
							}
						],
						"url": {
							"raw": "localhost:3000/produtos",
							"host": [
								"localhost"
							],
							"port": "3000",
							"path": [
								"produtos"
							]
						}
					},
					"response": []
				},
				{
					"name": "localhost:3000/produtos/1",
					"request": {
						"auth": {
							"type": "noauth"
						},
						"method": "GET",
						"header": [
							{
								"key": "Content-Type",
								"name": "Content-Type",
								"value": "application/json",
								"type": "text"
							}
						],
						"url": {
							"raw": "localhost:3000/produtos/1",
							"host": [
								"localhost"
							],
							"port": "3000",
							"path": [
								"produtos",
								"1"
							]
						}
					},
					"response": []
				},
				{
					"name": "localhost:3000/produtos/1",
					"request": {
						"auth": {
							"type": "bearer",
							"bearer": [
								{
									"key": "token",
									"value": "eyJhbGciOiJIUzI1NiIsInR5cCI6IkpXVCJ9.eyJpZCI6MiwiZW1haWwiOiJhbmFAZW1haWwuY29tIiwiaWF0IjoxNTc4MjQ3MjY5LCJleHAiOjE1NzgzMzM2Njl9.WBb_IE6e6VRCTHtQslhqSO-6uCAk_IDibRzh1Q56VjY",
									"type": "string"
								}
							]
						},
						"method": "PUT",
						"header": [
							{
								"key": "Content-Type",
								"name": "Content-Type",
								"value": "application/json",
								"type": "text"
							}
						],
						"body": {
							"mode": "raw",
							"raw": "{\n\t\"descricao\": \"Produto atualizado\",\n\t\"quantidade\": 50,\n\t\"valor\": 5,\n\t\"categoriaId\": 2\n}",
							"options": {
								"raw": {
									"language": "json"
								}
							}
						},
						"url": {
							"raw": "localhost:3000/produtos/1",
							"host": [
								"localhost"
							],
							"port": "3000",
							"path": [
								"produtos",
								"1"
							]
						}
					},
					"response": []
				},
				{
					"name": "localhost:3000/produtos/1",
					"request": {
						"auth": {
							"type": "bearer",
							"bearer": [
								{
									"key": "token",
									"value": "eyJhbGciOiJIUzI1NiIsInR5cCI6IkpXVCJ9.eyJpZCI6MiwiZW1haWwiOiJhbmFAZW1haWwuY29tIiwiaWF0IjoxNTc4MjQ3MjY5LCJleHAiOjE1NzgzMzM2Njl9.WBb_IE6e6VRCTHtQslhqSO-6uCAk_IDibRzh1Q56VjY",
									"type": "string"
								}
							]
						},
						"method": "DELETE",
						"header": [
							{
								"key": "Content-Type",
								"name": "Content-Type",
								"value": "application/json",
								"type": "text"
							}
						],
						"url": {
							"raw": "localhost:3000/produtos/1",
							"host": [
								"localhost"
							],
							"port": "3000",
							"path": [
								"produtos",
								"1"
							]
						}
					},
					"response": []
				}
			],
			"protocolProfileBehavior": {}
		},
		{
			"name": "Pedidos",
			"item": [
				{
					"name": "localhost:3000/pedidos",
					"request": {
						"auth": {
							"type": "bearer",
							"bearer": [
								{
									"key": "token",
									"value": "eyJhbGciOiJIUzI1NiIsInR5cCI6IkpXVCJ9.eyJpZCI6MiwiZW1haWwiOiJhbmFAZW1haWwuY29tIiwiaWF0IjoxNTc4MjQ4MzI3LCJleHAiOjE1NzgzMzQ3Mjd9.iG5S_wr89s9YOUVeK50ZV_pJr2RwUGDA6-0kwEt_x2U",
									"type": "string"
								}
							]
						},
						"method": "POST",
						"header": [
							{
								"key": "Content-Type",
								"name": "Content-Type",
								"value": "application/json",
								"type": "text"
							}
						],
						"body": {
							"mode": "raw",
							"raw": "{\n\t\"clienteId\": 2,\n\t\"produtos\": [{\n\t\t\"id\": 2,\n\t\t\"quantidade\": 5\n\t},\n\t{\n\t\t\"id\": 3,\n\t\t\"quantidade\": 10\n\t}]\n}",
							"options": {
								"raw": {
									"language": "json"
								}
							}
						},
						"url": {
							"raw": "localhost:3000/pedidos",
							"host": [
								"localhost"
							],
							"port": "3000",
							"path": [
								"pedidos"
							]
						}
					},
					"response": []
				},
				{
					"name": "localhost:3000/pedidos",
					"request": {
						"auth": {
							"type": "bearer",
							"bearer": [
								{
									"key": "token",
									"value": "eyJhbGciOiJIUzI1NiIsInR5cCI6IkpXVCJ9.eyJpZCI6MiwiZW1haWwiOiJhbmFAZW1haWwuY29tIiwiaWF0IjoxNTc4MjQ4MzI3LCJleHAiOjE1NzgzMzQ3Mjd9.iG5S_wr89s9YOUVeK50ZV_pJr2RwUGDA6-0kwEt_x2U",
									"type": "string"
								}
							]
						},
						"method": "GET",
						"header": [
							{
								"key": "Content-Type",
								"name": "Content-Type",
								"value": "application/json",
								"type": "text"
							}
						],
						"url": {
							"raw": "localhost:3000/pedidos",
							"host": [
								"localhost"
							],
							"port": "3000",
							"path": [
								"pedidos"
							]
						}
					},
					"response": []
				},
				{
					"name": "localhost:3000/pedidos/1",
					"request": {
						"auth": {
							"type": "bearer",
							"bearer": [
								{
									"key": "token",
									"value": "eyJhbGciOiJIUzI1NiIsInR5cCI6IkpXVCJ9.eyJpZCI6MiwiZW1haWwiOiJhbmFAZW1haWwuY29tIiwiaWF0IjoxNTc4MjQ4MzI3LCJleHAiOjE1NzgzMzQ3Mjd9.iG5S_wr89s9YOUVeK50ZV_pJr2RwUGDA6-0kwEt_x2U",
									"type": "string"
								}
							]
						},
						"method": "GET",
						"header": [
							{
								"key": "Content-Type",
								"name": "Content-Type",
								"value": "application/json",
								"type": "text"
							}
						],
						"url": {
							"raw": "localhost:3000/pedidos/1",
							"host": [
								"localhost"
							],
							"port": "3000",
							"path": [
								"pedidos",
								"1"
							]
						}
					},
					"response": []
				},
				{
					"name": "localhost:3000/pedidos/1",
					"request": {
						"auth": {
							"type": "bearer",
							"bearer": [
								{
									"key": "token",
									"value": "eyJhbGciOiJIUzI1NiIsInR5cCI6IkpXVCJ9.eyJpZCI6MiwiZW1haWwiOiJhbmFAZW1haWwuY29tIiwiaWF0IjoxNTc4MjQ4MzI3LCJleHAiOjE1NzgzMzQ3Mjd9.iG5S_wr89s9YOUVeK50ZV_pJr2RwUGDA6-0kwEt_x2U",
									"type": "string"
								}
							]
						},
						"method": "DELETE",
						"header": [
							{
								"key": "Content-Type",
								"name": "Content-Type",
								"value": "application/json",
								"type": "text"
							}
						],
						"url": {
							"raw": "localhost:3000/pedidos/1",
							"host": [
								"localhost"
							],
							"port": "3000",
							"path": [
								"pedidos",
								"1"
							]
						}
					},
					"response": []
				}
			],
			"protocolProfileBehavior": {}
		}
	],
	"protocolProfileBehavior": {}
}